notion_py/__init__.py
notion_py/cli.py
notion_py/notion_py.py
notionpy-0.1.0.dist-info/entry_points.txt
notionpy-0.1.0.dist-info/LICENSE
notionpy-0.1.0.dist-info/WHEEL
notionpy-0.1.0.dist-info/METADATA
notionpy-0.1.0.dist-info/RECORD
